envira/__init__.py
envira/__main__.py
envira/_version.py
envira/cli/README.md
envira/cli/__init__.py
envira/cli/installer.py
envira/cli/models.py
envira/cli/runner.py
envira/cli/steps.py
envira/cli/ui.py
envira/cli/utils.py
envira/software/__init__.py
envira/software/base.py
envira/software/essentials.py
envira/util/__init__.py
envira/util/const.py
envira/util/impl_dispatcher.py
envira/util/result.py
envira-0.0.0.dist-info/licenses/LICENSE
envira-0.0.0.dist-info/METADATA
envira-0.0.0.dist-info/WHEEL
envira-0.0.0.dist-info/entry_points.txt
envira-0.0.0.dist-info/top_level.txt
envira-0.0.0.dist-info/RECORD
