Metadata-Version: 2.4
Name: envira
Version: 0.0.0
Summary: A software environment management tool
Author-email: ControlNet <smczx@hotmail.com>
License:                     GNU AFFERO GENERAL PUBLIC LICENSE
Project-URL: Homepage, https://github.com/ControlNet/envira
Project-URL: Repository, https://github.com/ControlNet/envira
Project-URL: Issues, https://github.com/ControlNet/envira/issues
Classifier: Intended Audience :: Developers
Classifier: License :: OSI Approved :: GNU Affero General Public License v3
Classifier: Programming Language :: Python :: 3
Classifier: Programming Language :: Python :: 3.13
Classifier: Environment :: Console
Classifier: Operating System :: POSIX :: Linux
Classifier: Topic :: System :: Systems Administration
Classifier: Topic :: Utilities
Requires-Python: >=3.13.3
License-File: LICENSE
Requires-Dist: rich<15,>=14.0.0
Requires-Dist: distro<2,>=1.9.0
Dynamic: license-file
